moe/__init__.py
moe/data/__init__.py
moe/data/alpha.py
moe/data/feature.py
moe/data/timeseries.py
moe/metric/__init__.py
moe/metric/metric.py
moe/model/__init__.py
moe/model/layer.py
ml_moe-0.3.dist-info/LICENSE
ml_moe-0.3.dist-info/METADATA
ml_moe-0.3.dist-info/WHEEL
ml_moe-0.3.dist-info/top_level.txt
ml_moe-0.3.dist-info/RECORD
