Metadata-Version: 2.1
Name: ml-moe
Version: 0.3
Summary: Mixture of Experts
Home-page: https://github.com/shagunsodhani/moe
Author: Shagun Sodhani
Author-email: sshagunsodhani@gmail.com
License: UNKNOWN
Platform: UNKNOWN
Classifier: Programming Language :: Python :: 3.8
Classifier: Programming Language :: Python :: 3.9
Classifier: License :: OSI Approved :: MIT License
Classifier: Operating System :: OS Independent
Requires-Python: >=3.8
License-File: LICENSE
Provides-Extra: dev
